pz_rail_astro_tools-1.1.3.dist-info/licenses/LICENSE
rail/astro_tools/__init__.py
rail/astro_tools/_version.py
rail/creation/degraders/grid_selection.py
rail/creation/degraders/observing_condition_degrader.py
rail/creation/degraders/photometric_errors.py
rail/creation/degraders/spectroscopic_degraders.py
rail/creation/degraders/spectroscopic_selections.py
rail/creation/degraders/unrec_bl_model.py
rail/creation/engines/gcr_engine.py
rail/examples_data/creation_data/data/HSC_grid_settings.pkl
rail/examples_data/creation_data/data/hsc_ratios_and_specz.hdf5
rail/examples_data/creation_data/data/survey_conditions/DC2-dr6-galcounts-i20-i25.3-nside-128.fits
rail/examples_data/creation_data/data/survey_conditions/DC2-mask-neg-nside-128.fits
rail/examples_data/creation_data/data/survey_conditions/minion_1016_dc2_Median_airmass_i_and_nightlt1825_HEAL.fits
rail/examples_data/creation_data/data/survey_conditions/minion_1016_dc2_Median_fiveSigmaDepth_i_and_nightlt1825_HEAL.fits
rail/examples_data/testdata/rubin_dm_dc2_example2.pq
rail/pipelines/degradation/apply_phot_errors.py
rail/pipelines/degradation/blending.py
rail/pipelines/degradation/spectroscopic_selection_pipeline.py
rail/pipelines/degradation/truth_to_observed.py
rail/tools/photometry_tools.py
pz_rail_astro_tools-1.1.3.dist-info/METADATA
pz_rail_astro_tools-1.1.3.dist-info/WHEEL
pz_rail_astro_tools-1.1.3.dist-info/top_level.txt
pz_rail_astro_tools-1.1.3.dist-info/RECORD
