Metadata-Version: 2.4
Name: pz-rail-astro-tools
Version: 1.1.3
Author-email: "LSST Dark Energy Science Collaboration (DESC)" <lsst-desc-rail-admin@slac.stanford.edu>
License: MIT License
Classifier: Development Status :: 4 - Beta
Classifier: License :: OSI Approved :: MIT License
Classifier: Intended Audience :: Developers
Classifier: Intended Audience :: Science/Research
Classifier: Operating System :: OS Independent
Classifier: Programming Language :: Python
Requires-Python: >=3.9
License-File: LICENSE
Requires-Dist: deprecated
Requires-Dist: pz-rail-base>=1.0.3
Requires-Dist: numpy
Requires-Dist: pandas>=2.2.2
Requires-Dist: astropy
Requires-Dist: healpy
Requires-Dist: photerr>=1.4.0
Requires-Dist: dustmaps
Requires-Dist: pz-hyperbolic-temp
Requires-Dist: lsstdesc-gcr-catalogs
Requires-Dist: FoFCatalogMatching
Provides-Extra: dev
Requires-Dist: tables-io[full]; extra == "dev"
Requires-Dist: pytest; extra == "dev"
Requires-Dist: pytest-cov; extra == "dev"
Requires-Dist: pre-commit; extra == "dev"
Requires-Dist: pylint; extra == "dev"
Dynamic: license-file
